SerKosach153501/__init__.py
SerKosach153501/constans.py
SerKosach153501/fabric_ser.py
SerKosach153501/json_ser.py
SerKosach153501/sezializer.py
SerKosach153501/xml_ser.py
SerKosach153501-0.1.0.dist-info/METADATA
SerKosach153501-0.1.0.dist-info/WHEEL
SerKosach153501-0.1.0.dist-info/top_level.txt
SerKosach153501-0.1.0.dist-info/RECORD
